<?xml version="1.0" encoding="UTF-8"?>
<!-- vi:set ts=4 sw=4 noexpandtab: -->

<document>

	<properties>
		<title>Changes</title>
		<author email="frank@lin-k.net">Frank Cornelis</author>
	</properties>

	<body>

		<release version="1.0-SNAPSHOT" date="in SVN"
			desc="Initial release.">
			<action type="add" dev="fcorneli">
				Authentication web service client component.
			</action>
			<action type="add" dev="fcorneli">
				PKCS#12 keystore util component.
			</action>
			<action type="add" dev="fcorneli">
				Various servlet container login filters.
			</action>
			<action type="add" dev="fcorneli">
				JAAS login module for SafeOnline.
			</action>
			<action type="add" dev="fcorneli">
				Attribute web service client component.
			</action>
			<action type="add" dev="fcorneli">
				Data web service client component.
			</action>
		</release>

	</body>

</document>
